onelinerise/__init__.py
onelinerise/onelineriser.py
onelinerise-1.0.0.dist-info/LICENSE
onelinerise-1.0.0.dist-info/METADATA
onelinerise-1.0.0.dist-info/WHEEL
onelinerise-1.0.0.dist-info/top_level.txt
onelinerise-1.0.0.dist-info/RECORD
