Metadata-Version: 2.1
Name: onelinerise
Version: 1.0.0
Summary: Write oneline python code easily and have fun
Home-page: https://github.com/Jus-Codin/OneLinerise
Author: Jus-Codin
License: Unlicense
Platform: UNKNOWN
Classifier: Programming Language :: Python
Classifier: Development Status :: 5 - Production/Stable
Classifier: Natural Language :: English
Classifier: Operating System :: OS Independent
Classifier: Programming Language :: Python :: 3.8
Classifier: Programming Language :: Python :: 3.9
Classifier: Programming Language :: Python :: 3.10
Requires-Python: >=3.8.0
License-File: LICENSE
